{
  "project_info": {
    "project_number": "944282421467",
    "project_id": "berserkerweightlifting-2da28",
    "storage_bucket": "berserkerweightlifting-2da28.appspot.com"
  },
  "client": [
    {
      "client_info": {
        "mobilesdk_app_id": "1:944282421467:android:bede4b7126e447ed0fe4fe",
        "android_client_info": {
          "package_name": "com.android.application"
        }
      },
      "oauth_client": [
        {
          "client_id": "944282421467-e3q3ao3juu3escm612e3q61ct6oh9t1r.apps.googleusercontent.com",
          "client_type": 3
        }
      ],
      "api_key": [
        {
          "current_key": "AIzaSyCdSwPmM7Md8u1NOXhC_xQGfM2JsoOI2qo"
        }
      ],
      "services": {
        "appinvite_service": {
          "other_platform_oauth_client": [
            {
              "client_id": "944282421467-e3q3ao3juu3escm612e3q61ct6oh9t1r.apps.googleusercontent.com",
              "client_type": 3
            }
          ]
        }
      }
    }
  ],
  "configuration_version": "1"
}